rolling_pin/__init__.py
rolling_pin/blob_etl.py
rolling_pin/command.py
rolling_pin/conform_config.py
rolling_pin/conform_etl.py
rolling_pin/py.typed
rolling_pin/radon_etl.py
rolling_pin/repo_etl.py
rolling_pin/toml_etl.py
rolling_pin/tools.py
rolling_pin-0.11.2.dist-info/entry_points.txt
rolling_pin-0.11.2.dist-info/WHEEL
rolling_pin-0.11.2.dist-info/METADATA
rolling_pin-0.11.2.dist-info/licenses/LICENSE
rolling_pin-0.11.2.dist-info/RECORD
