Metadata-Version: 2.1
Name: rolling-pin
Version: 0.11.2
Summary: A library of generic tools for ETL work and visualization of JSON blobs and python repositories
License: MIT
Keywords: ETL,blob,dependency,graph,svg,networkx,transform,code metrics,dependency diagram,build system
Author-email: Alex Braun <alexander.g.braun@gmail.com>
Requires-Python: >=3.10
Classifier: Development Status :: 4 - Beta
Classifier: Intended Audience :: Developers
Classifier: License :: OSI Approved :: MIT License
Classifier: Programming Language :: Python :: 3
Classifier: Programming Language :: Python :: 3.10
Classifier: Programming Language :: Python :: 3.11
Classifier: Programming Language :: Python :: 3.12
Classifier: Programming Language :: Python :: 3.13
Classifier: Typing :: Typed
Requires-Dist: click>=8.1.3
Requires-Dist: graphviz
Requires-Dist: ipython
Requires-Dist: lunchbox>=0.6.1
Requires-Dist: networkx
Requires-Dist: numpy>=1.23.4
Requires-Dist: pandas>=1.1.5
Requires-Dist: plotly>=5.22.0
Requires-Dist: pydot>=1.4.2
Requires-Dist: pyyaml
Requires-Dist: radon<6.0.0
Requires-Dist: schematics
Requires-Dist: toml>=0.10.2
Requires-Dist: wrapt
Project-URL: documentation, https://theNewFlesh.github.io/rolling-pin
Project-URL: repository, https://github.com/theNewFlesh/rolling-pin
